{"countries":{"FR":{"n":"FRANCE","z":1,"f":1},"GP":{"n":"GUADELOUPE","z":1,"f":1},"MQ":{"n":"MARTINIQUE","z":1,"f":1},"GF":{"n":"GUYANE","z":1,"f":1},"RE":{"n":"RÉUNION","z":1,"f":1},"GI":{"n":"GIBRALTAR","a":[["2016-01-01","EUR","132"]]},"SX":{"n":"SAINT-MARTIN","z":1,"f":1},"MF":{"n":"SAINT-MARTIN","z":1,"f":1},"BL":{"n":"SAINT-BARTHÉLEMY","z":1,"f":1},"CD":{"n":"RÉP. DU CONGO","a":[["2009-10-21","EUR","195"]]},"CF":{"n":"RÉP. CENTRAFICAINE","a":[["2013-10-30","XAF","80000"]]},"CZ":{"n":"RÉP. TCHEQUE","a":[["2007-04-26","EUR","180"]],"z":1},"DO":{"n":"RÉP. DOMINICAINE","a":[["2006-11-01","USD","142"]]},"MH":{"n":"ILES MARSHALL","a":[["2006-11-01","USD","154"]]},"SB":{"n":"ILES SALOMON","a":[["2006-11-01","VUV","23052"]]},"SS":{"n":"SOUDAN DU SUD","a":[["2013-10-30","USD","306"]]},"LC":{"n":"SAINTE-LUCIE ET…","a":[["2006-11-01","USD","199"]]},"YE":{"n":"RÉP. DU YEMEN","a":[["2006-11-01","EUR","188"]]},"EU":{"n":"EUROPE (FORFAIT)","a":[["2019-01-01","EUR","156"]]},"GL":{"n":"DK-Groenland","a":[["2017-01-01","EUR","0"]]},"GG":{"n":"GB-Guernesey","a":[["2017-01-01","EUR","0"]]},"JE":{"n":"GB-Jersey","a":[["2017-01-01","EUR","0"]]},"IM":{"n":"GB-Île de Man","a":[["2017-01-01","EUR","0"]]},"FK":{"n":"GB-Îles Falkland","a":[["2017-01-01","EUR","0"]]},"FO":{"n":"DK-Féroé, îles","a":[["2017-01-01","EUR","0"]]},"IO":{"n":"GB-Indien (Territoire britannique de l'océan)","a":[["2017-01-01","EUR","0"]]},"EH":{"n":"MA-Sahara occidental","a":[["2017-01-01","EUR","0"]]},"TC":{"n":"GB-Îles Turques et Caïques","a":[["2017-01-01","EUR","0"]]},"AS":{"n":"US-Samoa américaines","a":[["2017-01-01","EUR","0"]]},"MP":{"n":"US-Îles Mariannes du Nord","a":[["2017-01-01","EUR","0"]]},"GU":{"n":"US-Guam","a":[["2017-01-01","EUR","0"]]},"UM":{"n":"US-Îles Mineures éloignées des États-Unis","a":[["2017-01-01","EUR","0"]]},"VI":{"n":"US-Îles vierges des Etats-Unis","a":[["2017-01-01","EUR","0"]]},"PR":{"n":"US-Porto Rico","a":[["2017-01-01","EUR","0"]]},"BQ":{"n":"NL-Bonaire, Saint-Eustache et Saba","a":[["2017-01-01","EUR","0"]]},"MS":{"n":"GB-Montserrat","a":[["2017-01-01","EUR","0"]]},"VG":{"n":"GB-Îles Vierges britanniques","a":[["2017-01-01","EUR","0"]]},"CX":{"n":"AU-Christmas, île","a":[["2017-01-01","EUR","0"]]},"NF":{"n":"AU-Île Norfolk","a":[["2017-01-01","EUR","0"]]},"AQ":{"n":"ANTARTIQUE","a":[["2017-01-01","EUR","0"]]},"AD":{"n":"ANDORRE","a":[["2006-11-01","EUR","118"]],"z":1},"AE":{"n":"EMIRATS ARABES UNIS","a":[["2008-12-10","EUR","300"]]},"AF":{"n":"AFGHANISTAN","a":[["2006-11-01","USD","279"]]},"AG":{"n":"ANTIGUA","a":[["2013-10-30","USD","230"]]},"AI":{"n":"ANGUILLA","a":[["2013-10-30","USD","208"]]},"AL":{"n":"ALBANIE","a":[["2018-07-20","EUR","130"]],"z":1},"AM":{"n":"ARMENIE","a":[["2007-04-26","EUR","186"]]},"AO":{"n":"ANGOLA","a":[["2009-10-21","EUR","300"]]},"AR":{"n":"ARGENTINE","a":[["2006-11-01","USD","157"]]},"AT":{"n":"AUTRICHE","a":[["2008-12-10","EUR","175"]],"z":1,"f":1},"AU":{"n":"AUSTRALIE","a":[["2007-04-26","AUD","348"]]},"AW":{"n":"ARUBA","a":[["2006-11-01","USD","150"]]},"AZ":{"n":"AZERBAIDJAN","a":[["2006-11-01","EUR","204"]]},"BA":{"n":"BOSNIE-HERZEGOVINE","a":[["2006-11-01","EUR","169"]],"z":1},"BB":{"n":"BARBADE","a":[["2006-11-01","USD","310"]]},"BD":{"n":"BANGLADESH","a":[["2018-07-20","EUR","258"]]},"BE":{"n":"BELGIQUE","a":[["2006-11-01","EUR","143"]],"z":1,"f":1},"BF":{"n":"BURKINA FASO","a":[["2008-12-10","EUR","145"]]},"BG":{"n":"BULGARIE","a":[["2006-11-01","EUR","145"]],"z":1},"BH":{"n":"BAHREIN","a":[["2008-12-10","EUR","200"]]},"BI":{"n":"BURUNDI","a":[["2009-10-21","EUR","140"]]},"BJ":{"n":"BENIN","a":[["2008-12-10","EUR","145"]]},"BM":{"n":"BERMUDES","a":[["2006-11-01","BMD","194"]]},"BN":{"n":"BRUNEI DARUSSALAM","a":[["2006-11-01","BND","255"]]},"BO":{"n":"BOLIVIE","a":[["2013-10-30","USD","135"]]},"BR":{"n":"BRESIL","a":[["2013-10-30","EUR","216"]]},"BS":{"n":"BAHAMAS","a":[["2006-11-01","USD","207"]]},"BT":{"n":"BHOUTAN","a":[["2017-01-01","EUR","0"]]},"BW":{"n":"BOTSWANA","a":[["2010-05-22","EUR","119"]]},"BX":{"n":"BRUXELLES","a":[["2006-11-01","EUR","46"]]},"BY":{"n":"BIELORUSSIE","a":[["2009-10-21","EUR","150"]]},"BZ":{"n":"BELIZE","a":[["2006-11-01","USD","177"]]},"CA":{"n":"CANADA","a":[["2006-11-01","CAD","260"]]},"CC":{"n":"CURACAO","a":[["2006-11-01","USD","150"]]},"CG":{"n":"CONGO","a":[["2006-11-01","XAF","69880"]]},"CH":{"n":"SUISSE","a":[["2006-11-01","CHF","230"]],"z":1},"CI":{"n":"COTE D'IVOIRE","a":[["2007-04-26","XOF","137000"]]},"CK":{"n":"COOK","a":[["2018-07-20","NZD","400"]]},"CL":{"n":"CHILI","a":[["2013-10-30","USD","217"]]},"CM":{"n":"CAMEROUN","a":[["2008-12-10","EUR","120"]]},"CN":{"n":"CHINE","a":[["2010-05-22","CNY","1700"]]},"CO":{"n":"COLOMBIE","a":[["2006-11-01","USD","176"]]},"CR":{"n":"COSTA RICA","a":[["2006-11-01","USD","169"]]},"CS":{"n":"SERBIE-MONTENEGRO","a":[["2007-04-26","EUR","150"]]},"CU":{"n":"CUBA","a":[["2018-07-20","EUR","200"]]},"CV":{"n":"CAP-VERT","a":[["2006-11-01","CVE","13575"]]},"CW":{"n":"CURACAO","a":[["2013-01-01","USD","150"]]},"CY":{"n":"CHYPRE","a":[["2008-12-10","EUR","190"]],"z":1,"f":1},"DE":{"n":"ALLEMAGNE","a":[["2006-11-01","EUR","164"]],"z":1,"f":1},"DJ":{"n":"DJIBOUTI","a":[["2006-11-01","DJF","36320"]]},"DK":{"n":"DANEMARK","a":[["2006-11-01","DKK","1660"]],"z":1},"DM":{"n":"DOMINIQUE","a":[["2013-10-30","USD","201"]]},"DZ":{"n":"ALGERIE","a":[["2018-07-20","DZD","20480"]],"z":1},"EC":{"n":"EQUATEUR","a":[["2006-11-01","USD","150"]]},"EE":{"n":"ESTONIE","a":[["2006-11-01","EUR","129"]],"f":1},"EG":{"n":"EGYPTE","a":[["2007-04-26","EUR","148"]]},"ER":{"n":"ERYTHREE","a":[["2018-07-20","USD","195"]]},"ES":{"n":"ESPAGNE","a":[["2006-11-01","EUR","132"]],"z":1,"f":1},"ET":{"n":"ETHIOPIE","a":[["2007-04-26","EUR","123"]]},"FI":{"n":"FINLANDE","a":[["2006-11-01","EUR","220"]],"z":1,"f":1},"FJ":{"n":"FIDJI","a":[["2006-11-01","FJD","224"]]},"FM":{"n":"MICRONESIE","a":[["2006-11-01","USD","157"]]},"GA":{"n":"GABON","a":[["2018-07-20","XAF","140000"]]},"GB":{"n":"GRANDE-BRETAGNE","a":[["2018-07-20","GBP","180"]],"z":1},"GD":{"n":"GRENADE","a":[["2013-10-30","USD","199"]]},"GE":{"n":"GEORGIE","a":[["2006-11-01","USD","195"]]},"GH":{"n":"GHANA","a":[["2018-07-20","USD","250"]]},"GM":{"n":"GAMBIE","a":[["2006-11-01","GMD","2460"]]},"GN":{"n":"GUINEE","a":[["2013-10-30","EUR","170"]]},"GQ":{"n":"GUINEE EQUATORIALE","a":[["2006-11-01","XAF","90500"]]},"GR":{"n":"GRECE","a":[["2006-11-01","EUR","167"]],"z":1,"f":1},"GT":{"n":"GUATEMALA","a":[["2009-10-21","EUR","160"]]},"GW":{"n":"GUINEE BISSAU","a":[["2006-11-01","EUR","105"]]},"GY":{"n":"GUYANA","a":[["2006-11-01","USD","200"]]},"HK":{"n":"HONG-KONG","a":[["2010-05-22","HKD","2200"]]},"HN":{"n":"HONDURAS","a":[["2006-11-01","USD","152"]]},"HR":{"n":"CROATIE","a":[["2008-12-10","EUR","142"]],"z":1},"HT":{"n":"HAITI","a":[["2007-04-26","USD","220"]]},"HU":{"n":"HONGRIE","a":[["2008-12-10","EUR","175"]],"z":1},"ID":{"n":"INDONESIE","a":[["2009-10-21","EUR","160"]]},"IE":{"n":"IRLANDE","a":[["2007-04-26","EUR","190"]],"z":1,"f":1},"IL":{"n":"ISRAEL","a":[["2013-10-30","EUR","230"]]},"IN":{"n":"INDE","a":[["2018-07-20","EUR","210"]]},"IQ":{"n":"IRAK","a":[["2007-04-26","EUR","300"]]},"IR":{"n":"IRAN","a":[["2007-04-26","USD","186"]]},"IS":{"n":"ISLANDE","a":[["2018-07-20","ISK","34397"]]},"IT":{"n":"ITALIE","a":[["2008-12-10","EUR","220"]],"z":1,"f":1},"JM":{"n":"JAMAIQUE","a":[["2006-11-01","USD","162"]]},"JO":{"n":"JORDANIE","a":[["2007-10-31","JOD","151"]]},"JP":{"n":"JAPON","a":[["2013-10-30","JPY","25500"]]},"KE":{"n":"KENYA","a":[["2006-11-01","USD","141"]]},"KG":{"n":"KIRGHIZIE","a":[["2009-10-21","EUR","150"]]},"KH":{"n":"CAMBODGE","a":[["2006-11-01","USD","150"]]},"KI":{"n":"KIRIBATI","a":[["2006-11-01","FJD","221"]]},"KM":{"n":"COMORES","a":[["2008-12-10","EUR","150"]]},"KN":{"n":"SAINT-KITTS-ET-NEVIS","a":[["2013-10-30","USD","202"]]},"KP":{"n":"COREE DU NORD","a":[["2006-11-01","USD","272"]]},"KR":{"n":"COREE DU SUD","a":[["2008-12-10","EUR","210"]]},"KW":{"n":"KOWEIT","a":[["2008-12-10","EUR","245"]]},"KY":{"n":"CAIMANS","a":[["2006-11-01","USD","141"]]},"KZ":{"n":"KAZAKHSTAN","a":[["2009-10-21","EUR","290"]]},"LA":{"n":"LAOS","a":[["2013-10-30","USD","150"]]},"LB":{"n":"LIBAN","a":[["2006-11-01","EUR","154"]]},"LG":{"n":"LUXEMBOURG","a":[["2006-11-01","EUR","50"]]},"LI":{"n":"LIECHTENSTEIN","a":[["2006-11-01","CHF","230"]]},"LK":{"n":"SRI LANKA","a":[["2018-07-20","EUR","180"]]},"LR":{"n":"LIBERIA","a":[["2013-10-30","USD","230"]]},"LS":{"n":"LESOTHO","a":[["2010-05-22","EUR","120"]]},"LT":{"n":"LITUANIE","a":[["2018-07-20","EUR","145"]],"f":1},"LU":{"n":"LUXEMBOURG","a":[["2008-12-10","EUR","173"]],"z":1,"f":1},"LV":{"n":"LETTONIE","a":[["2006-11-01","EUR","152"]],"f":1},"LY":{"n":"LIBYE","a":[["2013-10-30","LYD","280"]]},"MA":{"n":"MAROC","a":[["2009-10-21","EUR","175"]],"z":1},"MD":{"n":"MOLDAVIE","a":[["2006-11-01","USD","188"]]},"ME":{"n":"MONTENEGRO","a":[["2008-12-10","EUR","150"]]},"MG":{"n":"MADAGASCAR","a":[["2006-11-01","EUR","114"]]},"MK":{"n":"MACEDOINE","a":[["2007-04-26","EUR","117"]],"z":1},"ML":{"n":"MALI","a":[["2006-11-01","XOF","62000"]]},"MM":{"n":"BIRMANIE","a":[["2013-10-30","USD","250"]]},"MN":{"n":"MONGOLIE EXTERIEURE","a":[["2006-11-01","EUR","102"]]},"MO":{"n":"MACAO","a":[["2010-05-22","HKD","2200"]]},"MR":{"n":"MAURITANIE","a":[["2008-12-10","EUR","143"]]},"MT":{"n":"MALTE","a":[["2008-12-10","EUR","105"]],"z":1,"f":1},"MU":{"n":"MAURICE","a":[["2013-10-30","MUR","5500"]]},"MV":{"n":"MALDIVES","a":[["2018-07-20","EUR","320"]]},"MW":{"n":"MALAWI","a":[["2006-11-01","USD","214"]]},"MX":{"n":"MEXIQUE","a":[["2009-10-21","EUR","150"]]},"MY":{"n":"MALAISIE","a":[["2007-10-31","MYR","468"]]},"MZ":{"n":"MOZAMBIQUE","a":[["2006-11-01","USD","189"]]},"NA":{"n":"NAMIBIE","a":[["2009-10-21","EUR","90"]]},"NC":{"n":"NOUVELLE-CALEDONIE","a":[["2017-01-01","EUR","120"]]},"NE":{"n":"NIGER","a":[["2006-11-01","XOF","78000"]]},"NG":{"n":"NIGERIA","a":[["2010-05-22","EUR","273"]]},"NI":{"n":"NICARAGUA","a":[["2006-11-01","USD","154"]]},"NL":{"n":"PAYS-BAS","a":[["2006-11-01","EUR","161"]],"z":1,"f":1},"NO":{"n":"NORVEGE","a":[["2006-11-01","NOK","1465"]],"z":1},"NP":{"n":"NEPAL","a":[["2006-11-01","USD","140"]]},"NR":{"n":"NAURU","a":[["2006-11-01","FJD","208"]]},"NU":{"n":"NIUE","a":[["2006-11-01","NZD","204"]]},"NY":{"n":"NEW-YORK CITY","a":[["2019-09-01","USD","450"],["2019-01-01","USD","320"]]},"NZ":{"n":"NOUVELLE-ZELANDE","a":[["2006-11-01","NZD","370"]]},"OM":{"n":"OMAN","a":[["2008-12-10","EUR","265"]]},"PA":{"n":"PANAMA","a":[["2006-11-01","USD","178"]]},"PE":{"n":"PEROU","a":[["2006-11-01","USD","170"]]},"PF":{"n":"POLYNESIE FRANCAISE","a":[["2017-01-01","EUR","120"]]},"PG":{"n":"NOUVELLE-GUINEE PAPOUASIE","a":[["2008-12-10","EUR","172"]]},"PH":{"n":"PHILIPPINES","a":[["2006-11-01","PHP","8770"]]},"PK":{"n":"PAKISTAN","a":[["2006-11-01","USD","173"]]},"PL":{"n":"POLOGNE","a":[["2009-10-21","EUR","175"]],"z":1},"PM":{"n":"SAINT-PIERRE-ET-MIQUELON","z":1,"f":1},"PT":{"n":"PORTUGAL","a":[["2007-04-26","EUR","160"]],"z":1,"f":1},"PW":{"n":"ILES PALAOS","a":[["2006-11-01","USD","311"]]},"PY":{"n":"PARAGUAY","a":[["2007-04-26","USD","180"]]},"QA":{"n":"QATAR","a":[["2007-04-26","EUR","278"]]},"RO":{"n":"ROUMANIE","a":[["2009-10-21","EUR","160"]],"z":1},"RS":{"n":"SERBIE","a":[["2008-12-10","EUR","150"]]},"RU":{"n":"RUSSIE","a":[["2007-04-26","EUR","230"]]},"RW":{"n":"RWANDA","a":[["2013-10-30","USD","277"]]},"SA":{"n":"ARABIE SAOUDITE","a":[["2008-12-10","EUR","158"]]},"SC":{"n":"SEYCHELLES","a":[["2009-10-21","EUR","300"]]},"SD":{"n":"SOUDAN","a":[["2006-11-01","USD","175"]]},"SE":{"n":"SUEDE","a":[["2006-11-01","SEK","1997"]],"z":1},"SG":{"n":"SINGAPOUR","a":[["2008-12-10","EUR","200"]]},"SH":{"n":"SHANGHAI","a":[["2010-11-01","CNY","1700"]]},"SI":{"n":"SLOVENIE","a":[["2009-10-21","EUR","160"]],"z":1,"f":1},"SK":{"n":"SLOVAQUIE","a":[["2010-05-22","EUR","155"]],"z":1,"f":1},"SL":{"n":"SIERRA LEONE","a":[["2006-11-01","USD","260"]]},"SN":{"n":"SENEGAL","a":[["2006-11-01","XOF","91800"]]},"SO":{"n":"SOMALIE","a":[["2006-11-01","USD","158"]]},"SR":{"n":"SURINAM","a":[["2006-11-01","USD","180"]]},"ST":{"n":"SAO TOME-ET-PRINCIPE","a":[["2006-11-01","USD","135"]]},"SV":{"n":"SALVADOR","a":[["2006-11-01","USD","177"]]},"SY":{"n":"SYRIE","a":[["2010-05-22","EUR","154"]]},"SZ":{"n":"SWAZILAND","a":[["2018-07-20","EUR","138"]]},"TD":{"n":"TCHAD","a":[["2008-12-10","EUR","225"]]},"TG":{"n":"TOGO","a":[["2007-10-31","XOF","82640"]]},"TH":{"n":"THAILANDE","a":[["2018-07-20","THB","5000"]]},"TI":{"n":"TIMOR EST","a":[["2009-10-21","EUR","150"]]},"TJ":{"n":"TADJIKISTAN","a":[["2018-07-20","USD","250"]]},"TM":{"n":"TURKMENISTAN","a":[["2006-11-01","EUR","102"]]},"TN":{"n":"TUNISIE","a":[["2009-10-21","EUR","125"]],"z":1},"TO":{"n":"TONGA","a":[["2006-11-01","FJD","214"]]},"TR":{"n":"TURQUIE","a":[["2008-12-10","EUR","165"]]},"TT":{"n":"TRINITE ET TOBAGO","a":[["2006-11-01","USD","267"]]},"TV":{"n":"TUVALU","a":[["2006-11-01","FJD","192"]]},"TW":{"n":"TAIWAN","a":[["2006-11-01","TWD","5990"]]},"TY":{"n":"TOKYO","a":[["2013-10-30","JPY","30000"]]},"TZ":{"n":"TANZANIE","a":[["2009-10-21","EUR","135"]]},"UA":{"n":"UKRAINE","a":[["2006-11-01","EUR","208"]]},"UG":{"n":"OUGANDA","a":[["2009-10-21","EUR","130"]]},"US":{"n":"ETATS-UNIS","a":[["2010-05-22","USD","320"]]},"UY":{"n":"URUGUAY","a":[["2006-11-01","USD","135"]]},"UZ":{"n":"OUZBEKISTAN","a":[["2018-07-20","USD","197"]]},"VC":{"n":"SAINT-VINCENT","a":[["2006-11-01","USD","188"]]},"VE":{"n":"VENEZUELA","a":[["2008-12-10","EUR","195"]]},"VN":{"n":"VIETNAM","a":[["2008-12-10","EUR","158"]]},"VU":{"n":"VANUATU","a":[["2009-10-21","EUR","210"]]},"WF":{"n":"WALLIS ET FUTUNA, ILES","a":[["2017-01-01","EUR","120"]]},"WS":{"n":"SAMOA OCCIDENTALES","a":[["2018-07-20","USD","230"]]},"XK":{"n":"KOSOVO","a":[["2018-07-20","EUR","150"],["2017-01-01","EUR","0"]]},"YT":{"n":"MAYOTTE","z":1,"f":1},"YU":{"n":"YOUGOSLAVIE","a":[["2003-01-01","USD","136"]],"z":1},"ZA":{"n":"AFRIQUE DU SUD","a":[["2019-03-01","EUR","138"],["2018-12-15","EUR","185"]]},"ZM":{"n":"ZAMBIE","a":[["2009-10-21","EUR","180"]]},"ZW":{"n":"ZIMBABWE","a":[["2013-10-30","USD","180"]]},"TL":{"n":"TIMOR EST","a":[["2009-10-21","EUR","150"]]}},"exr":{"EUR":["1.0000","1.0000","1.0000"],"XAF":["655.9570","655.9570","655.9570"],"XOF":["655.9570","655.9570","655.9570"],"DKK":["7.4673","7.4715","7.4694"],"GBP":["0.8945","0.8508","0.8727"],"HKD":["8.9675","8.7473","8.8574"],"ISK":["133.2000","135.8000","134.5000"],"JPY":["125.8500","121.9400","123.8950"],"MYR":["4.7317","4.5953","4.6635"],"NOK":["9.9483","9.8638","9.9061"],"NZD":["1.7056","1.6653","1.6854"],"PHP":["60.1130","56.9000","58.5065"],"BMD":["1.1467","1.1214","1.1341"],"BND":["1.5629","1.5084","1.5356"],"CVE":["110.2650","110.2650","110.2650"],"DJF":["204.0896","199.5815","201.8356"],"DZD":["135.3370","133.6415","134.4892"],"FJD":["2.4608","2.4046","2.4327"],"SEK":["10.2548","10.4468","10.3508"],"THB":["37.0520","33.4150","35.2335"],"USD":["1.1450","1.1234","1.1342"],"TWD":["34.9674","33.6679","34.3177"],"VUV":["128.7333","128.2367","128.4850"],"MUR":["39.3337","40.7580","40.0459"],"GMD":["56.6191","57.4693","57.0442"],"JOD":["0.8140","0.7950","0.8045"],"LYD":["1.5976","1.5699","1.5837"],"AUD":["1.6220","1.5995","1.6107"],"CAD":["1.5605","1.4598","1.5101"],"CHF":["1.1269","1.0854","1.1061"],"CNY":["7.8751","7.8205","7.8478"]},"year":"2019","zoneForfaitEuro":["AT","BE","BL","CY","DE","EE","ES","FI","FR","GF","GP","GR","IE","IT","LT","LU","LV","MF","MQ","MT","NL","PM","PT","RE","SI","SK","SX","YT"],"maxForfait10":12627}